Metadata-Version: 2.1
Name: woebin-python
Version: 0.1.9
Summary: UNKNOWN
Home-page: UNKNOWN
License: MIT
Platform: UNKNOWN
